apistar_pagination/__init__.py
apistar_pagination/__init__.py
apistar_pagination/http.py
apistar_pagination/http.py
apistar_pagination/schemas.py
apistar_pagination/schemas.py
apistar_pagination-0.4.0.dist-info/LICENSE
apistar_pagination-0.4.0.dist-info/WHEEL
apistar_pagination-0.4.0.dist-info/METADATA
apistar_pagination-0.4.0.dist-info/RECORD
