Metadata-Version: 2.1
Name: apistar-pagination
Version: 0.4.0
Summary: Pagination tools for API Star.
Home-page: https://github.com/PeRDy/apistar-pagination
License: GPL-3.0+
Keywords: apistar,pagination
Author: José Antonio Perdiguero López
Author-email: perdy@perdy.io
Requires-Python: >=3.5,<4.0
Classifier: License :: OSI Approved :: GNU General Public License v3 or later (GPLv3+)
Classifier: Programming Language :: Python :: 3
Classifier: Programming Language :: Python :: 3.5
Classifier: Programming Language :: Python :: 3.6
Classifier: Programming Language :: Python :: 3.7
Requires-Dist: apistar (>=0.5.30,<0.6.0)
